LICENSE.txt
MANIFEST.in
README.rst
setup.cfg
setup.py
describe_it/__init__.py
describe_it/noseplugin.py
describe_it.egg-info/PKG-INFO
describe_it.egg-info/SOURCES.txt
describe_it.egg-info/dependency_links.txt
describe_it.egg-info/entry_points.txt
describe_it.egg-info/pbr.json
describe_it.egg-info/requires.txt
describe_it.egg-info/top_level.txt