Metadata-Version: 1.0
Name: describe-it
Version: 2.2.2
Summary: A nose plugin that supports writing describe/it style unit tests with nested contexts
Home-page: https://github.com/joakimkarlsson/describe_it
Author: Joakim Karlsson
Author-email: joakim@jkarlsson.com
License: The MIT License (MIT)
